{
    "boxShadow": "{{appsmith.theme.boxShadow.appBoxShadow}}",
    "borderColor": "#E0DEDE",
    "isVisibleDownload": true,
    "iconSVG": "/static/media/icon.e6911f8bb94dc6c4a102a74740c41763.svg",
    "topRow": 46,
    "isSortable": true,
    "type": "TABLE_WIDGET_V2",
    "inlineEditingSaveOption": "ROW_LEVEL",
    "animateLoading": true,
    "dynamicBindingPathList": [
        {"key": "accentColor"},
        {"key": "borderRadius"},
        {"key": "boxShadow"},
        {"key": "tableData"},
        {"key": "primaryColumns.licensePlate.computedValue"},
        {"key": "primaryColumns.make.computedValue"},
        {"key": "primaryColumns.model.computedValue"},
        {"key": "primaryColumns.type.computedValue"},
        {"key": "primaryColumns.passengerSeats.computedValue"},
        {"key": "primaryColumns.color.computedValue"},
        {"key": "primaryColumns.owner.computedValue"}
    ],
    "needsHeightForContent": true,
    "leftColumn": 1,
    "delimiter": ",",
    "defaultSelectedRowIndex": 0,
    "flexVerticalAlignment": "start",
    "accentColor": "{{appsmith.theme.colors.primaryColor}}",
    "isVisibleFilters": true,
    "isVisible": true,
    "enableClientSideSearch": true,
    "version": 2,
    "totalRecordsCount": 0,
    "tags": [
        "Suggested",
        "Display"
    ],
    "isLoading": false,
    "childStylesheet": {
        "button": {
            "boxShadow": "none",
            "borderRadius": "{{appsmith.theme.borderRadius.appBorderRadius}}",
            "buttonColor": "{{appsmith.theme.colors.primaryColor}}"
        },
        "iconButton": {
            "boxShadow": "none",
            "borderRadius": "{{appsmith.theme.borderRadius.appBorderRadius}}",
            "buttonColor": "{{appsmith.theme.colors.primaryColor}}"
        },
        "menuButton": {
            "boxShadow": "none",
            "borderRadius": "{{appsmith.theme.borderRadius.appBorderRadius}}",
            "menuColor": "{{appsmith.theme.colors.primaryColor}}"
        },
        "editActions": {
            "saveButtonColor": "{{appsmith.theme.colors.primaryColor}}",
            "saveBorderRadius": "{{appsmith.theme.borderRadius.appBorderRadius}}",
            "discardBorderRadius": "{{appsmith.theme.borderRadius.appBorderRadius}}",
            "discardButtonColor": "{{appsmith.theme.colors.primaryColor}}"
        }
    },
    "borderRadius": "{{appsmith.theme.borderRadius.appBorderRadius}}",
    "columnUpdatedAt": 1698996237734,
    "originalBottomRow": 84,
    "defaultSelectedRowIndices": [0],
    "mobileBottomRow": 50,
    "widgetName": "Table1",
    "defaultPageSize": 0,
    "columnOrder": [
        "licensePlate",
        "make",
        "model",
        "type",
        "passengerSeats",
        "color",
        "owner"
    ],
    "dynamicPropertyPathList": [],
    "displayName": "Table",
    "bottomRow": 84,
    "columnWidthMap": {},
    "parentRowSpace": 10,
    "hideCard": false,
    "mobileRightColumn": 36,
    "parentColumnSpace": 13.046875,
    "dynamicTriggerPathList": [],
    "borderWidth": "1",
    "primaryColumns": {
        "owner": {
            "computedValue": "{{Table1.processedTableData.map((currentRow, currentIndex) => ( currentRow[\"owner\"]))}}",
            "isEditable": false,
            "alias": "owner",
            "enableSort": true,
            "isSaveVisible": true,
            "id": "owner",
            "isDisabled": false,
            "allowSameOptionsInNewRow": true,
            "validation": {},
            "isCellVisible": true,
            "isDerived": false,
            "textSize": "0.875rem",
            "allowCellWrapping": false,
            "index": 6,
            "isDiscardVisible": true,
            "isVisible": false,
            "label": "owner",
            "columnType": "text",
            "horizontalAlignment": "LEFT",
            "isCellEditable": false,
            "width": 150,
            "enableFilter": true,
            "sticky": "",
            "originalId": "owner",
            "verticalAlignment": "CENTER"
        },
        "licensePlate": {
            "computedValue": "{{Table1.processedTableData.map((currentRow, currentIndex) => ( currentRow[\"licensePlate\"]))}}",
            "isEditable": false,
            "alias": "licensePlate",
            "enableSort": true,
            "isSaveVisible": true,
            "id": "licensePlate",
            "isDisabled": false,
            "allowSameOptionsInNewRow": true,
            "validation": {},
            "isCellVisible": true,
            "isDerived": false,
            "textSize": "0.875rem",
            "allowCellWrapping": false,
            "index": 0,
            "isDiscardVisible": true,
            "isVisible": true,
            "label": "licensePlate",
            "columnType": "text",
            "horizontalAlignment": "LEFT",
            "isCellEditable": false,
            "width": 150,
            "enableFilter": true,
            "sticky": "",
            "originalId": "licensePlate",
            "verticalAlignment": "CENTER"
        },
        "passengerSeats": {
            "computedValue": "{{Table1.processedTableData.map((currentRow, currentIndex) => ( currentRow[\"passengerSeats\"]))}}",
            "isEditable": false,
            "alias": "passengerSeats",
            "enableSort": true,
            "isSaveVisible": true,
            "id": "passengerSeats",
            "isDisabled": false,
            "allowSameOptionsInNewRow": true,
            "validation": {},
            "isCellVisible": true,
            "isDerived": false,
            "textSize": "0.875rem",
            "allowCellWrapping": false,
            "index": 4,
            "isDiscardVisible": true,
            "isVisible": true,
            "label": "passengerSeats",
            "columnType": "number",
            "horizontalAlignment": "LEFT",
            "isCellEditable": false,
            "width": 150,
            "enableFilter": true,
            "sticky": "",
            "originalId": "passengerSeats",
            "verticalAlignment": "CENTER"
        },
        "color": {
            "computedValue": "{{Table1.processedTableData.map((currentRow, currentIndex) => ( currentRow[\"color\"]))}}",
            "isEditable": false,
            "alias": "color",
            "enableSort": true,
            "isSaveVisible": true,
            "id": "color",
            "isDisabled": false,
            "allowSameOptionsInNewRow": true,
            "validation": {},
            "isCellVisible": true,
            "isDerived": false,
            "textSize": "0.875rem",
            "allowCellWrapping": false,
            "index": 5,
            "isDiscardVisible": true,
            "isVisible": true,
            "label": "color",
            "columnType": "text",
            "horizontalAlignment": "LEFT",
            "isCellEditable": false,
            "width": 150,
            "enableFilter": true,
            "sticky": "",
            "originalId": "color",
            "verticalAlignment": "CENTER"
        },
        "model": {
            "computedValue": "{{Table1.processedTableData.map((currentRow, currentIndex) => ( currentRow[\"model\"]))}}",
            "isEditable": false,
            "alias": "model",
            "enableSort": true,
            "isSaveVisible": true,
            "id": "model",
            "isDisabled": false,
            "allowSameOptionsInNewRow": true,
            "validation": {},
            "isCellVisible": true,
            "isDerived": false,
            "textSize": "0.875rem",
            "allowCellWrapping": false,
            "index": 2,
            "isDiscardVisible": true,
            "isVisible": true,
            "label": "model",
            "columnType": "text",
            "horizontalAlignment": "LEFT",
            "isCellEditable": false,
            "width": 150,
            "enableFilter": true,
            "sticky": "",
            "originalId": "model",
            "verticalAlignment": "CENTER"
        },
        "type": {
            "computedValue": "{{Table1.processedTableData.map((currentRow, currentIndex) => ( currentRow[\"type\"]))}}",
            "isEditable": false,
            "alias": "type",
            "enableSort": true,
            "isSaveVisible": true,
            "id": "type",
            "isDisabled": false,
            "allowSameOptionsInNewRow": true,
            "validation": {},
            "isCellVisible": true,
            "isDerived": false,
            "textSize": "0.875rem",
            "allowCellWrapping": false,
            "index": 3,
            "isDiscardVisible": true,
            "isVisible": true,
            "label": "type",
            "columnType": "text",
            "horizontalAlignment": "LEFT",
            "isCellEditable": false,
            "width": 150,
            "enableFilter": true,
            "sticky": "",
            "originalId": "type",
            "verticalAlignment": "CENTER"
        },
        "make": {
            "computedValue": "{{Table1.processedTableData.map((currentRow, currentIndex) => ( currentRow[\"make\"]))}}",
            "isEditable": false,
            "alias": "make",
            "enableSort": true,
            "isSaveVisible": true,
            "id": "make",
            "isDisabled": false,
            "allowSameOptionsInNewRow": true,
            "validation": {},
            "isCellVisible": true,
            "isDerived": false,
            "textSize": "0.875rem",
            "allowCellWrapping": false,
            "index": 1,
            "isDiscardVisible": true,
            "isVisible": true,
            "label": "make",
            "columnType": "text",
            "horizontalAlignment": "LEFT",
            "isCellEditable": false,
            "width": 150,
            "enableFilter": true,
            "sticky": "",
            "originalId": "make",
            "verticalAlignment": "CENTER"
        }
    },
    "key": "ms7cn7z5k3",
    "canFreezeColumn": true,
    "isDeprecated": false,
    "rightColumn": 62,
    "textSize": "0.875rem",
    "widgetId": "ermsybw3fj",
    "allowAddNewRow": true,
    "minWidth": 450,
    "tableData": "{{GetAllVehicle.data}}",
    "label": "Data",
    "searchKey": "",
    "parentId": "0",
    "renderMode": "CANVAS",
    "mobileTopRow": 22,
    "horizontalAlignment": "LEFT",
    "isVisibleSearch": true,
    "responsiveBehavior": "fill",
    "originalTopRow": 46,
    "mobileLeftColumn": 2,
    "isVisiblePagination": true,
    "verticalAlignment": "CENTER"
}